openapigateway/__init__.py
openapigateway/constructs.py
openapigateway-0.2.1.dist-info/LICENSE.txt
openapigateway-0.2.1.dist-info/METADATA
openapigateway-0.2.1.dist-info/WHEEL
openapigateway-0.2.1.dist-info/top_level.txt
openapigateway-0.2.1.dist-info/RECORD
