Metadata-Version: 2.1
Name: openapigateway
Version: 0.2.1
Summary: AWS CDK Construct that creates an Amazon API Gateway HttpApi based on a parameterized OpenAPI 3 Document.
Home-page: https://github.com/suud/cdk-openapigateway
Author: Timo Sutterer
Author-email: hi@timo-sutterer.de
License: UNKNOWN
Platform: UNKNOWN
Classifier: Development Status :: 4 - Beta
Classifier: Intended Audience :: Developers
Classifier: License :: OSI Approved :: MIT License
Classifier: Programming Language :: Python :: 3 :: Only
Classifier: Programming Language :: Python :: 3.6
Classifier: Programming Language :: Python :: 3.7
Classifier: Programming Language :: Python :: 3.8
Classifier: Framework :: AWS CDK
Classifier: Framework :: AWS CDK :: 1
Classifier: Topic :: Software Development :: Code Generators
Classifier: Topic :: Utilities
Classifier: Operating System :: OS Independent
Requires-Python: >=3.6
Requires-Dist: PyYAML
Requires-Dist: aws-cdk.core (>=1.79.0)
Requires-Dist: aws-cdk.aws-apigatewayv2 (>=1.79.0)
Provides-Extra: dev
Requires-Dist: wheel (==0.36.2) ; extra == 'dev'
Requires-Dist: twine (==3.3.0) ; extra == 'dev'
Requires-Dist: bump2version (==1.0.1) ; extra == 'dev'
